CMSCouchapp-1.3.4.data/data/couchapp/LICENSE
CMSCouchapp-1.3.4.data/data/couchapp/MANIFEST.in
CMSCouchapp-1.3.4.data/data/couchapp/NOTICE
CMSCouchapp-1.3.4.data/data/couchapp/README.rst
CMSCouchapp-1.3.4.data/data/couchapp/THANKS
couchapp/__init__.py
couchapp/client.py
couchapp/commands.py
couchapp/config.py
couchapp/errors.py
couchapp/localdoc.py
couchapp/macros.py
couchapp/util.py
CMSCouchapp-1.3.4.dist-info/LICENSE
CMSCouchapp-1.3.4.dist-info/METADATA
CMSCouchapp-1.3.4.dist-info/NOTICE
CMSCouchapp-1.3.4.dist-info/WHEEL
CMSCouchapp-1.3.4.dist-info/entry_points.txt
CMSCouchapp-1.3.4.dist-info/top_level.txt
CMSCouchapp-1.3.4.dist-info/RECORD
