Metadata-Version: 2.1
Name: CMSCouchapp
Version: 1.3.4
Summary: Standalone CouchDB Application Development Made Simple.
Home-page: http://github.com/amaltaro/couchapp
Author: Alan Malta
Author-email: alan.malta@cern.ch
License: Apache License 2
Keywords: couchdb couchapp
Platform: unix
Classifier: License :: OSI Approved :: Apache Software License
Classifier: Intended Audience :: Developers
Classifier: Intended Audience :: System Administrators
Classifier: Development Status :: 4 - Beta
Classifier: Programming Language :: Python :: 3.8
Classifier: Operating System :: POSIX
Classifier: Topic :: Database
Classifier: Topic :: Utilities
Requires-Dist: requests (>=2.20.0)
